{"nodes": [{"id": "c_users_maury_onedrive_desktop_code_country_edu_project_eventflow_eventflow_frontend_src_utils_helpers_js", "label": "helpers.js", "file_type": "code", "source_file": "C:\\Users\\maury\\OneDrive\\Desktop\\CODE\\Country Edu Project\\EventFlow\\eventflow-frontend\\src\\utils\\helpers.js", "source_location": "L1"}, {"id": "helpers_formatdate", "label": "formatDate()", "file_type": "code", "source_file": "C:\\Users\\maury\\OneDrive\\Desktop\\CODE\\Country Edu Project\\EventFlow\\eventflow-frontend\\src\\utils\\helpers.js", "source_location": "L3"}, {"id": "helpers_formattime", "label": "formatTime()", "file_type": "code", "source_file": "C:\\Users\\maury\\OneDrive\\Desktop\\CODE\\Country Edu Project\\EventFlow\\eventflow-frontend\\src\\utils\\helpers.js", "source_location": "L10"}, {"id": "helpers_formatprice", "label": "formatPrice()", "file_type": "code", "source_file": "C:\\Users\\maury\\OneDrive\\Desktop\\CODE\\Country Edu Project\\EventFlow\\eventflow-frontend\\src\\utils\\helpers.js", "source_location": "L17"}, {"id": "helpers_truncate", "label": "truncate()", "file_type": "code", "source_file": "C:\\Users\\maury\\OneDrive\\Desktop\\CODE\\Country Edu Project\\EventFlow\\eventflow-frontend\\src\\utils\\helpers.js", "source_location": "L22"}, {"id": "helpers_getinitials", "label": "getInitials()", "file_type": "code", "source_file": "C:\\Users\\maury\\OneDrive\\Desktop\\CODE\\Country Edu Project\\EventFlow\\eventflow-frontend\\src\\utils\\helpers.js", "source_location": "L25"}, {"id": "helpers_rolecolor", "label": "roleColor()", "file_type": "code", "source_file": "C:\\Users\\maury\\OneDrive\\Desktop\\CODE\\Country Edu Project\\EventFlow\\eventflow-frontend\\src\\utils\\helpers.js", "source_location": "L28"}, {"id": "helpers_statuscolor", "label": "statusColor()", "file_type": "code", "source_file": "C:\\Users\\maury\\OneDrive\\Desktop\\CODE\\Country Edu Project\\EventFlow\\eventflow-frontend\\src\\utils\\helpers.js", "source_location": "L32"}], "edges": [{"source": "c_users_maury_onedrive_desktop_code_country_edu_project_eventflow_eventflow_frontend_src_utils_helpers_js", "target": "helpers_formatdate", "relation": "contains", "confidence": "EXTRACTED", "source_file": "C:\\Users\\maury\\OneDrive\\Desktop\\CODE\\Country Edu Project\\EventFlow\\eventflow-frontend\\src\\utils\\helpers.js", "source_location": "L3", "weight": 1.0}, {"source": "c_users_maury_onedrive_desktop_code_country_edu_project_eventflow_eventflow_frontend_src_utils_helpers_js", "target": "helpers_formattime", "relation": "contains", "confidence": "EXTRACTED", "source_file": "C:\\Users\\maury\\OneDrive\\Desktop\\CODE\\Country Edu Project\\EventFlow\\eventflow-frontend\\src\\utils\\helpers.js", "source_location": "L10", "weight": 1.0}, {"source": "c_users_maury_onedrive_desktop_code_country_edu_project_eventflow_eventflow_frontend_src_utils_helpers_js", "target": "helpers_formatprice", "relation": "contains", "confidence": "EXTRACTED", "source_file": "C:\\Users\\maury\\OneDrive\\Desktop\\CODE\\Country Edu Project\\EventFlow\\eventflow-frontend\\src\\utils\\helpers.js", "source_location": "L17", "weight": 1.0}, {"source": "c_users_maury_onedrive_desktop_code_country_edu_project_eventflow_eventflow_frontend_src_utils_helpers_js", "target": "helpers_truncate", "relation": "contains", "confidence": "EXTRACTED", "source_file": "C:\\Users\\maury\\OneDrive\\Desktop\\CODE\\Country Edu Project\\EventFlow\\eventflow-frontend\\src\\utils\\helpers.js", "source_location": "L22", "weight": 1.0}, {"source": "c_users_maury_onedrive_desktop_code_country_edu_project_eventflow_eventflow_frontend_src_utils_helpers_js", "target": "helpers_getinitials", "relation": "contains", "confidence": "EXTRACTED", "source_file": "C:\\Users\\maury\\OneDrive\\Desktop\\CODE\\Country Edu Project\\EventFlow\\eventflow-frontend\\src\\utils\\helpers.js", "source_location": "L25", "weight": 1.0}, {"source": "c_users_maury_onedrive_desktop_code_country_edu_project_eventflow_eventflow_frontend_src_utils_helpers_js", "target": "helpers_rolecolor", "relation": "contains", "confidence": "EXTRACTED", "source_file": "C:\\Users\\maury\\OneDrive\\Desktop\\CODE\\Country Edu Project\\EventFlow\\eventflow-frontend\\src\\utils\\helpers.js", "source_location": "L28", "weight": 1.0}, {"source": "c_users_maury_onedrive_desktop_code_country_edu_project_eventflow_eventflow_frontend_src_utils_helpers_js", "target": "helpers_statuscolor", "relation": "contains", "confidence": "EXTRACTED", "source_file": "C:\\Users\\maury\\OneDrive\\Desktop\\CODE\\Country Edu Project\\EventFlow\\eventflow-frontend\\src\\utils\\helpers.js", "source_location": "L32", "weight": 1.0}], "raw_calls": [{"caller_nid": "helpers_formatdate", "callee": "toLocaleDateString", "source_file": "C:\\Users\\maury\\OneDrive\\Desktop\\CODE\\Country Edu Project\\EventFlow\\eventflow-frontend\\src\\utils\\helpers.js", "source_location": "L5"}, {"caller_nid": "helpers_formattime", "callee": "toLocaleTimeString", "source_file": "C:\\Users\\maury\\OneDrive\\Desktop\\CODE\\Country Edu Project\\EventFlow\\eventflow-frontend\\src\\utils\\helpers.js", "source_location": "L12"}, {"caller_nid": "helpers_formatprice", "callee": "toFixed", "source_file": "C:\\Users\\maury\\OneDrive\\Desktop\\CODE\\Country Edu Project\\EventFlow\\eventflow-frontend\\src\\utils\\helpers.js", "source_location": "L19"}, {"caller_nid": "helpers_formatprice", "callee": "Number", "source_file": "C:\\Users\\maury\\OneDrive\\Desktop\\CODE\\Country Edu Project\\EventFlow\\eventflow-frontend\\src\\utils\\helpers.js", "source_location": "L19"}, {"caller_nid": "helpers_truncate", "callee": "slice", "source_file": "C:\\Users\\maury\\OneDrive\\Desktop\\CODE\\Country Edu Project\\EventFlow\\eventflow-frontend\\src\\utils\\helpers.js", "source_location": "L23"}, {"caller_nid": "helpers_getinitials", "callee": "toUpperCase", "source_file": "C:\\Users\\maury\\OneDrive\\Desktop\\CODE\\Country Edu Project\\EventFlow\\eventflow-frontend\\src\\utils\\helpers.js", "source_location": "L26"}, {"caller_nid": "helpers_getinitials", "callee": "join", "source_file": "C:\\Users\\maury\\OneDrive\\Desktop\\CODE\\Country Edu Project\\EventFlow\\eventflow-frontend\\src\\utils\\helpers.js", "source_location": "L26"}, {"caller_nid": "helpers_getinitials", "callee": "slice", "source_file": "C:\\Users\\maury\\OneDrive\\Desktop\\CODE\\Country Edu Project\\EventFlow\\eventflow-frontend\\src\\utils\\helpers.js", "source_location": "L26"}, {"caller_nid": "helpers_getinitials", "callee": "map", "source_file": "C:\\Users\\maury\\OneDrive\\Desktop\\CODE\\Country Edu Project\\EventFlow\\eventflow-frontend\\src\\utils\\helpers.js", "source_location": "L26"}, {"caller_nid": "helpers_getinitials", "callee": "split", "source_file": "C:\\Users\\maury\\OneDrive\\Desktop\\CODE\\Country Edu Project\\EventFlow\\eventflow-frontend\\src\\utils\\helpers.js", "source_location": "L26"}, {"caller_nid": "helpers_statuscolor", "callee": "toLowerCase", "source_file": "C:\\Users\\maury\\OneDrive\\Desktop\\CODE\\Country Edu Project\\EventFlow\\eventflow-frontend\\src\\utils\\helpers.js", "source_location": "L35"}]}